code_ingestion/__init__.py
code_ingestion/cli.py
code_ingestion/analyzers/__init__.py
code_ingestion/analyzers/cst_analyzer.py
code_ingestion/analyzers/java_analyzer.py
code_ingestion/analyzers/java_cst_types.py
code_ingestion/chunkers/__init__.py
code_ingestion/chunkers/code_chunker.py
code_ingestion/chunkers/factory.py
code_ingestion/chunking_strategies/__init__.py
code_ingestion/chunking_strategies/base_strategy.py
code_ingestion/chunking_strategies/smart_method_strategy.py
code_ingestion/data_models/__init__.py
code_ingestion/data_models/chunk_metadata.py
code_ingestion/data_models/class_info.py
code_ingestion/data_models/code_chunk.py
code_ingestion/data_models/method_info.py
code_ingestion/embeddings/__init__.py
code_ingestion/embeddings/base_provider.py
code_ingestion/embeddings/factory.py
code_ingestion/embeddings/provider.py
code_ingestion/enums/__init__.py
code_ingestion/enums/chunk_type.py
code_ingestion/enums/programming_language.py
code_ingestion/orchestration/__init__.py
code_ingestion/orchestration/ingestion_orchestrator.py
code_ingestion/parsers/__init__.py
code_ingestion/parsers/code_parser.py
code_ingestion/parsers/java_parser.py
code_ingestion/vector_stores/__init__.py
code_ingestion/vector_stores/base_store.py
code_ingestion/vector_stores/factory.py
code_ingestion/vector_stores/pinecone_store.py
code_ingestion_service-0.2.0.dist-info/licenses/LICENSE
code_ingestion_service-0.2.0.dist-info/METADATA
code_ingestion_service-0.2.0.dist-info/WHEEL
code_ingestion_service-0.2.0.dist-info/entry_points.txt
code_ingestion_service-0.2.0.dist-info/top_level.txt
code_ingestion_service-0.2.0.dist-info/RECORD
