Metadata-Version: 2.4
Name: code-ingestion-service
Version: 0.2.0
Summary: A production-ready Python service for intelligently chunking source code and ingesting it into RAG pipelines
Author-email: Sandeep G <sandeepg2890@gmail.com>
License: Apache-2.0
Project-URL: Homepage, https://github.com/sandeepgovi/code-ingestion-service
Project-URL: Issues, https://github.com/sandeepgovi/code-ingestion-service/issues
Project-URL: Repository, https://github.com/sandeepgovi/code-ingestion-service.git
Keywords: rag,code-analysis,embeddings,vector-database,code-chunking
Classifier: Development Status :: 5 - Production/Stable
Classifier: Intended Audience :: Developers
Classifier: License :: OSI Approved :: Apache Software License
Classifier: Programming Language :: Python :: 3
Classifier: Programming Language :: Python :: 3.11
Classifier: Programming Language :: Python :: 3.12
Classifier: Programming Language :: Python :: 3.13
Classifier: Topic :: Software Development :: Libraries :: Python Modules
Classifier: Topic :: Text Processing :: General
Classifier: Topic :: Scientific/Engineering :: Artificial Intelligence
Requires-Python: >=3.11
License-File: LICENSE
Requires-Dist: tree-sitter
Requires-Dist: tree-sitter-java
Requires-Dist: langchain
Requires-Dist: langchain-community
Requires-Dist: langchain-huggingface
Requires-Dist: gitpython
Requires-Dist: pydantic
Requires-Dist: python-dotenv
Requires-Dist: sentence-transformers
Requires-Dist: einops
Requires-Dist: pinecone
Requires-Dist: langchain-pinecone
Requires-Dist: langchain-nomic
Requires-Dist: nomic[local]
Requires-Dist: click
Provides-Extra: dev
Requires-Dist: pytest; extra == "dev"
Requires-Dist: black; extra == "dev"
Requires-Dist: mypy; extra == "dev"
Dynamic: license-file
